outline/__init__.py
outline/node_ancestry_item.py
outline/node_ancestry_record.py
outline/opml_exceptions.py
outline/outline.py
outline/outline_node.py
outline/outline_node_definition.py
outline/outline_utilities.py
outline_preprocessors/__init__.py
outline_preprocessors/preprocessor_generic.py
outline_preprocessors/preprocessor_text_indent.py
outlines_unleashed/__init__.py
outlines_unleashed/data_node_field_definition.py
outlines_unleashed/data_node_specifier.py
outlines_unleashed/data_node_specifier_v0_1.py
outlines_unleashed/data_node_specifier_v0_2.py
outlines_unleashed/data_node_table.py
outlines_unleashed/node_ancestry_matching_criteria.py
outlines_unleashed/outline_parser.py
outlines_unleashed/outline_unleashed_utilities.py
outlines_unleashed/tag_field_descriptor.py
outlines_unleashed/unleashed_node_ancestry_item.py
outlines_unleashed/unleashed_node_ancestry_record.py
outlines_unleashed/unleashed_outline.py
outlines_unleashed/unleashed_outline_exceptions.py
outlines_unleashed/unleashed_outline_node.py
output_generators/__init__.py
output_generators/csv_output_generator.py
output_generators/ppt_output_generator_generic.py
output_generators/ppt_output_generator_simple.py
output_generators/ppt_output_generators.py
resources/__init__.py
resources/test/json_serialized.py
tests/__init__.py
tests/outline/__init__.py
tests/outline_unleashed/__init__.py
tests/outline_unleashed/test_unleashed_outline_node.py
outlines_unleashed-0.0.18.dist-info/METADATA
outlines_unleashed-0.0.18.dist-info/WHEEL
outlines_unleashed-0.0.18.dist-info/top_level.txt
outlines_unleashed-0.0.18.dist-info/RECORD
