Metadata-Version: 2.4
Name: outlines-unleashed
Version: 0.0.18
Summary: Unleash the power of OPML and Outlines
Home-page: https://github.com/sevire/outlines-unleashed
Author: Thomas Gaylard
Author-email: thomas.gaylard@genonline.co.uk
License: TBD
Classifier: Programming Language :: Python :: 3
Classifier: License :: OSI Approved :: MIT License
Classifier: Operating System :: OS Independent
Requires-Python: >=3.6
Requires-Dist: ddt
Dynamic: author
Dynamic: author-email
Dynamic: classifier
Dynamic: description
Dynamic: description-content-type
Dynamic: home-page
Dynamic: license
Dynamic: requires-dist
Dynamic: requires-python
Dynamic: summary
